rosetta_dev_tools
