Metadata-Version: 1.1
Name: rosetta-dev-tools
Version: 1.1.0
Summary: A set of tools to facilitate development of the Rosetta protein design suite.
Home-page: https://github.com/Kortemme-Lab/rosetta_dev_tools
Author: Kale Kundert
Author-email: kale.kundert@ucsf.edu
License: MIT
Keywords: rosetta,protein,design
Platform: UNKNOWN
Classifier: Intended Audience :: Developers
Classifier: Programming Language :: Python :: 3
